{
  "@context": {
    "schema": "http://schema.org/",
    "example": "http://example.org/",
    "subjectOf": "schema:subjectOf",
    "hasRole": "example:hasRole",
    "name": "schema:name",
    "location": "schema:location",
    "authored": "example:authored",
    "authors": {
      "@id": "example:author",
      "@container": "@list"
    }
  },
  "@type": "schema:Person",
  "@id": "https://www.ggvaidya.com/",
  "authored": [
    {
      "@type": "http://okfnlabs.org/bibjson/",
      "@id": "https://doi.org/10.1080/10635150600969864",
      "doi": "10.1080/10635150600969864",
      "datePublished": "2006-10-01",
      "title": "DNA Barcoding and Taxonomy in Diptera: A Tale of High Intraspecific Variability and Low Identification Success",
      "authors": [
        {
          "@id": "https://www.dbs.nus.edu.sg/staffs/rudolf-meier/",
          "name": "Rudolf Meier",
          "firstname": "Rudolf",
          "lastname": "Meier"
        },
        {
          "@id": "https://www.linkedin.com/in/shiyang-kwong-b490a356/",
          "name": "Kwong Shiyang",
          "firstname": "Rudolf",
          "lastname": "Meier"
        },
        {
          "@id": "https://www.ggvaidya.com/",
          "name": "Gaurav Vaidya",
          "firstname": "Gaurav",
          "lastname": "Vaidya"
        },
        {
          "@id": "https://www.wikidata.org/wiki/Q21393244",
          "name": "Peter K. L. Ng",
          "firstname": "Peter",
          "middlename": "K. L.",
          "lastname": "Ng"
        }
      ],
      "journal": {
        "name": "Systematic Biology",
        "volume": 55,
        "issue": 5,
        "pages": "715--728"
      }
    },
    {
      "@type": "http://okfnlabs.org/bibjson/",
      "@id": "https://doi.org/10.1111/j.1096-0031.2010.00329.x",
      "doi": "10.1111/j.1096-0031.2010.00329.x",
      "datePublished": "2011-03-08",
      "title": "SequenceMatrix: concatenation software for the fast assembly of multi‐gene datasets with character set and codon information",
      "authors": [
        {
          "@id": "https://www.ggvaidya.com/",
          "name": "Gaurav Vaidya",
          "firstname": "Gaurav",
          "lastname": "Vaidya"
        },
        {
          "@id": "http://lohman.ccny.cuny.edu/",
          "name": "David J. Lohman",
          "firstname": "David",
          "middlename": "J.",
          "lastname": "Lohman"
        },
        {
          "@id": "https://www.dbs.nus.edu.sg/staffs/rudolf-meier/",
          "name": "Rudolf Meier",
          "firstname": "Rudolf",
          "lastname": "Meier"
        }
      ],
      "journal": {
        "name": "Cladistics",
        "volume": 27,
        "issue": 2,
        "pages": "171--180"
      }
    }
  ]
}
